[{
  "_id": {
    "$oid": "642f338e6b52e8b9f2e1240f"
  },
  "recipe": {
    "$oid": "640cd5ac2d9fecf12e8897f4"
  },
  "userId": {
    "$oid": "642f277c6b52e8b9f2e1228c"
  }
},
{
  "_id": {
    "$oid": "6430142209916576692b5d52"
  },
  "recipe": {
    "$oid": "640cd5ac2d9fecf12e8897f3"
  },
  "userId": {
    "$oid": "642f277c6b52e8b9f2e1228c"
  }
},
{
  "_id": {
    "$oid": "643017d309916576692b5dac"
  },
  "recipe": {
    "$oid": "640cd5ac2d9fecf12e8897f2"
  },
  "userId": {
    "$oid": "642f277c6b52e8b9f2e1228c"
  }
},
{
  "_id": {
    "$oid": "643052a9e2d754d8e3549c50"
  },
  "recipe": {
    "$oid": "640cd5ac2d9fecf12e8897f2"
  },
  "userId": {
    "$oid": "64304cefe24adc09604eb96c"
  }
},
{
  "_id": {
    "$oid": "643124149799b1abed6c9d82"
  },
  "recipe": {
    "$oid": "640cd5ac2d9fecf12e889808"
  },
  "userId": {
    "$oid": "64304cefe24adc09604eb96c"
  }
},
{
  "_id": {
    "$oid": "64312e399799b1abed6c9f08"
  },
  "recipe": {
    "$oid": "640cd5ac2d9fecf12e889838"
  },
  "userId": {
    "$oid": "64304cefe24adc09604eb96c"
  }
},
{
  "_id": {
    "$oid": "6431c93634a783fc11631100"
  },
  "recipe": {
    "$oid": "640cd5ac2d9fecf12e889808"
  },
  "userId": {
    "$oid": "6431593c6132383177606b83"
  }
},
{
  "_id": {
    "$oid": "6431cdf134a783fc1163155b"
  },
  "recipe": {
    "$oid": "640cd5ac2d9fecf12e8897f8"
  },
  "userId": {
    "$oid": "6431c7a334a783fc11631091"
  }
},
{
  "_id": {
    "$oid": "6431ce0534a783fc1163160a"
  },
  "recipe": {
    "$oid": "640cd5ac2d9fecf12e889808"
  },
  "userId": {
    "$oid": "6431c7a334a783fc11631091"
  }
},
{
  "_id": {
    "$oid": "6432f2c6630377a200442e49"
  },
  "recipe": {
    "$oid": "640cd5ac2d9fecf12e889808"
  },
  "userId": {
    "$oid": "6432c4ff630377a200442634"
  }
},
{
  "_id": {
    "$oid": "6432f2eb630377a200442e6f"
  },
  "recipe": {
    "$oid": "640cd5ac2d9fecf12e889803"
  },
  "userId": {
    "$oid": "6432c4ff630377a200442634"
  }
},
{
  "_id": {
    "$oid": "6432f4fd630377a200442ec6"
  },
  "recipe": {
    "$oid": "640cd5ac2d9fecf12e8898aa"
  },
  "userId": {
    "$oid": "6432c4ff630377a200442634"
  }
},
{
  "_id": {
    "$oid": "6432f6a1630377a200442f0f"
  },
  "recipe": {
    "$oid": "640cd5ac2d9fecf12e8897f8"
  },
  "userId": {
    "$oid": "64318c2a1834e4319c88e5e0"
  }
},
{
  "_id": {
    "$oid": "64341af5211310fde8f6e252"
  },
  "recipe": {
    "$oid": "640cd5ac2d9fecf12e889808"
  },
  "userId": {
    "$oid": "64341adf211310fde8f6e22e"
  }
},
{
  "_id": {
    "$oid": "64341afb211310fde8f6e265"
  },
  "recipe": {
    "$oid": "640cd5ac2d9fecf12e889855"
  },
  "userId": {
    "$oid": "64341adf211310fde8f6e22e"
  }
},
{
  "_id": {
    "$oid": "64341b01211310fde8f6e279"
  },
  "recipe": {
    "$oid": "640cd5ac2d9fecf12e8897f9"
  },
  "userId": {
    "$oid": "64341adf211310fde8f6e22e"
  }
},
{
  "_id": {
    "$oid": "64341b07211310fde8f6e292"
  },
  "recipe": {
    "$oid": "640cd5ac2d9fecf12e889831"
  },
  "userId": {
    "$oid": "64341adf211310fde8f6e22e"
  }
},
{
  "_id": {
    "$oid": "64343cb5211310fde8f6e726"
  },
  "recipe": {
    "$oid": "640cd5ac2d9fecf12e889838"
  },
  "userId": {
    "$oid": "64318c2a1834e4319c88e5e0"
  }
},
{
  "_id": {
    "$oid": "6435179898e56cf375a5f27a"
  },
  "recipe": {
    "$oid": "640cd5ac2d9fecf12e889808"
  },
  "userId": {
    "$oid": "64345134618ca0301fdaa53b"
  }
},
{
  "_id": {
    "$oid": "6435b1bfaa0afad3b044b816"
  },
  "recipe": {
    "$oid": "640cd5ac2d9fecf12e889808"
  },
  "userId": {
    "$oid": "643050fde2d754d8e3549c33"
  }
},
{
  "_id": {
    "$oid": "643670d6e993d9be986bbf42"
  },
  "recipe": {
    "$oid": "640cd5ac2d9fecf12e889805"
  },
  "userId": {
    "$oid": "64366ceee993d9be986bbf38"
  }
},
{
  "_id": {
    "$oid": "64367153e993d9be986bbf50"
  },
  "recipe": {
    "$oid": "640cd5ac2d9fecf12e8897f6"
  },
  "userId": {
    "$oid": "64366ceee993d9be986bbf38"
  }
},
{
  "_id": {
    "$oid": "64367180e993d9be986bbf6a"
  },
  "recipe": {
    "$oid": "640cd5ac2d9fecf12e88982e"
  },
  "userId": {
    "$oid": "64366ceee993d9be986bbf38"
  }
},
{
  "_id": {
    "$oid": "6436718be993d9be986bbf71"
  },
  "recipe": {
    "$oid": "640cd5ac2d9fecf12e889808"
  },
  "userId": {
    "$oid": "64366ceee993d9be986bbf38"
  }
},
{
  "_id": {
    "$oid": "643673de0d6d675de9d19671"
  },
  "recipe": {
    "$oid": "640cd5ac2d9fecf12e8898a3"
  },
  "userId": {
    "$oid": "64366faa0d6d675de9d19560"
  }
},
{
  "_id": {
    "$oid": "643674cd0d6d675de9d19692"
  },
  "recipe": {
    "$oid": "640cd5ac2d9fecf12e889863"
  },
  "userId": {
    "$oid": "6431c7a334a783fc11631091"
  }
},
{
  "_id": {
    "$oid": "643678b30d6d675de9d1980b"
  },
  "recipe": {
    "$oid": "640cd5ac2d9fecf12e88981f"
  },
  "userId": {
    "$oid": "64366faa0d6d675de9d19560"
  }
},
{
  "_id": {
    "$oid": "643678c40d6d675de9d1981f"
  },
  "recipe": {
    "$oid": "640cd5ac2d9fecf12e889855"
  },
  "userId": {
    "$oid": "64366faa0d6d675de9d19560"
  }
},
{
  "_id": {
    "$oid": "6436a515d33c2213c08eb07f"
  },
  "recipe": {
    "$oid": "640cd5ac2d9fecf12e8898a8"
  },
  "userId": {
    "$oid": "64317e9e2dafd51f9a37f32f"
  }
},
{
  "_id": {
    "$oid": "6436a532d33c2213c08eb0a1"
  },
  "recipe": {
    "$oid": "640cd5ac2d9fecf12e889852"
  },
  "userId": {
    "$oid": "64317e9e2dafd51f9a37f32f"
  }
},
{
  "_id": {
    "$oid": "6436a7b1d33c2213c08eb0f0"
  },
  "recipe": {
    "$oid": "640cd5ac2d9fecf12e889855"
  },
  "userId": {
    "$oid": "64317e9e2dafd51f9a37f32f"
  }
},
{
  "_id": {
    "$oid": "6436a7b7d33c2213c08eb111"
  },
  "recipe": {
    "$oid": "640cd5ac2d9fecf12e889849"
  },
  "userId": {
    "$oid": "64317e9e2dafd51f9a37f32f"
  }
},
{
  "_id": {
    "$oid": "6436a7cad33c2213c08eb13b"
  },
  "recipe": {
    "$oid": "640cd5ac2d9fecf12e889812"
  },
  "userId": {
    "$oid": "64317e9e2dafd51f9a37f32f"
  }
},
{
  "_id": {
    "$oid": "6436b85c3c7be23f4b47795f"
  },
  "recipe": {
    "$oid": "640cd5ac2d9fecf12e889808"
  },
  "userId": {
    "$oid": "6436b8223c7be23f4b4778ba"
  }
},
{
  "_id": {
    "$oid": "6436d4e270239e062781bc61"
  },
  "recipe": {
    "$oid": "640cd5ac2d9fecf12e889855"
  },
  "userId": {
    "$oid": "6436d4d070239e062781bc2c"
  }
},
{
  "_id": {
    "$oid": "6436da07513abaa88fd0619f"
  },
  "recipe": {
    "$oid": "640cd5ac2d9fecf12e889812"
  },
  "userId": {
    "$oid": "64366ceee993d9be986bbf38"
  }
},
{
  "_id": {
    "$oid": "6436dfb7022e40d47426b7fb"
  },
  "recipe": {
    "$oid": "640cd5ac2d9fecf12e889840"
  },
  "userId": {
    "$oid": "6431b8c51834e4319c89754b"
  }
},
{
  "_id": {
    "$oid": "6436e027022e40d47426b88d"
  },
  "recipe": {
    "$oid": "640cd5ac2d9fecf12e88981f"
  },
  "userId": {
    "$oid": "6431b8c51834e4319c89754b"
  }
},
{
  "_id": {
    "$oid": "6436e056022e40d47426b910"
  },
  "recipe": {
    "$oid": "6435eebd10a4676a48f8eab6"
  },
  "userId": {
    "$oid": "6431b8c51834e4319c89754b"
  }
},
{
  "_id": {
    "$oid": "6436e873022e40d47426bcaa"
  },
  "recipe": {
    "$oid": "640cd5ac2d9fecf12e889808"
  },
  "userId": {
    "$oid": "6431b8c51834e4319c89754b"
  }
},
{
  "_id": {
    "$oid": "64370a9a2196e2b90d2842da"
  },
  "recipe": {
    "$oid": "640cd5ac2d9fecf12e88981a"
  },
  "userId": {
    "$oid": "643709a72196e2b90d284259"
  }
},
{
  "_id": {
    "$oid": "643730f957a3eec20d2238e0"
  },
  "recipe": {
    "$oid": "640cd5ac2d9fecf12e889849"
  },
  "userId": {
    "$oid": "64307cdbe2d754d8e354a0a1"
  }
},
{
  "_id": {
    "$oid": "64383246c4567a907f303c9f"
  },
  "recipe": {
    "$oid": "640cd5ac2d9fecf12e8898a6"
  },
  "userId": {
    "$oid": "6431b8c51834e4319c89754b"
  }
},
{
  "_id": {
    "$oid": "6438420e42abc93e429498b6"
  },
  "recipe": {
    "$oid": "640cd5ac2d9fecf12e889855"
  },
  "userId": {
    "$oid": "6437f924bfee3943311833a2"
  }
},
{
  "_id": {
    "$oid": "6438431842abc93e42949951"
  },
  "recipe": {
    "$oid": "640cd5ac2d9fecf12e8898a9"
  },
  "userId": {
    "$oid": "6431b8c51834e4319c89754b"
  }
},
{
  "_id": {
    "$oid": "6438444842abc93e42949a17"
  },
  "recipe": {
    "$oid": "640cd5ac2d9fecf12e889835"
  },
  "userId": {
    "$oid": "6431b8c51834e4319c89754b"
  }
},
{
  "_id": {
    "$oid": "6438466542abc93e42949a87"
  },
  "recipe": {
    "$oid": "640cd5ac2d9fecf12e889808"
  },
  "userId": {
    "$oid": "6437e7d1dd8423aa43bb25fe"
  }
},
{
  "_id": {
    "$oid": "6438470e42abc93e42949ae7"
  },
  "recipe": {
    "$oid": "640cd5ac2d9fecf12e88984e"
  },
  "userId": {
    "$oid": "64307cdbe2d754d8e354a0a1"
  }
},
{
  "_id": {
    "$oid": "6438490642abc93e42949b4b"
  },
  "recipe": {
    "$oid": "640cd5ac2d9fecf12e889819"
  },
  "userId": {
    "$oid": "6431b8c51834e4319c89754b"
  }
},
{
  "_id": {
    "$oid": "64384e2842abc93e42949cc2"
  },
  "recipe": {
    "$oid": "640cd5ac2d9fecf12e889864"
  },
  "userId": {
    "$oid": "6431c7a334a783fc11631091"
  }
},
{
  "_id": {
    "$oid": "64397d8b9bdccd52144d1728"
  },
  "recipe": {
    "$oid": "640cd5ac2d9fecf12e8898df"
  },
  "userId": {
    "$oid": "6431b8c51834e4319c89754b"
  }
},
{
  "_id": {
    "$oid": "643beb43dde6d852bcbece4d"
  },
  "recipe": {
    "$oid": "640cd5ac2d9fecf12e889808"
  },
  "userId": {
    "$oid": "643be93ddde6d852bcbece24"
  }
},
{
  "_id": {
    "$oid": "643c39dfb7fc59e59f3391a8"
  },
  "recipe": {
    "$oid": "640cd5ac2d9fecf12e8898e2"
  },
  "userId": {
    "$oid": "6431b8c51834e4319c89754b"
  }
},
{
  "_id": {
    "$oid": "643cfe0d3b89d7f780ead2c0"
  },
  "recipe": {
    "$oid": "640cd5ac2d9fecf12e8897fd"
  },
  "userId": {
    "$oid": "64318c2a1834e4319c88e5e0"
  }
},
{
  "_id": {
    "$oid": "643d0c3f3b89d7f780ead4c8"
  },
  "recipe": {
    "$oid": "640cd5ac2d9fecf12e889825"
  },
  "userId": {
    "$oid": "64318c2a1834e4319c88e5e0"
  }
},
{
  "_id": {
    "$oid": "643d0c453b89d7f780ead4d6"
  },
  "recipe": {
    "$oid": "640cd5ac2d9fecf12e889839"
  },
  "userId": {
    "$oid": "64318c2a1834e4319c88e5e0"
  }
},
{
  "_id": {
    "$oid": "643d0c673b89d7f780ead50f"
  },
  "recipe": {
    "$oid": "640cd5ac2d9fecf12e889863"
  },
  "userId": {
    "$oid": "64318c2a1834e4319c88e5e0"
  }
},
{
  "_id": {
    "$oid": "643d4978e3899da37ca0eac1"
  },
  "recipe": {
    "$oid": "640cd5ac2d9fecf12e889804"
  },
  "userId": {
    "$oid": "6432ba9d630377a2004423d6"
  }
},
{
  "_id": {
    "$oid": "6443f9a4e19416a7bb1bdcfb"
  },
  "recipe": {
    "$oid": "640cd5ac2d9fecf12e889808"
  },
  "userId": {
    "$oid": "64383243c4567a907f303c92"
  }
},
{
  "_id": {
    "$oid": "644ef7041f620abb8ffab9a2"
  },
  "recipe": {
    "$oid": "640cd5ac2d9fecf12e889808"
  },
  "userId": {
    "$oid": "644ef6511f620abb8ffab96a"
  }
},
{
  "_id": {
    "$oid": "64789ea1a929c56fab48f2c3"
  },
  "recipe": {
    "$oid": "640cd5ac2d9fecf12e889811"
  },
  "userId": {
    "$oid": "64789e88a929c56fab48f296"
  }
},
{
  "_id": {
    "$oid": "64789eaca929c56fab48f2d7"
  },
  "recipe": {
    "$oid": "640cd5ac2d9fecf12e889826"
  },
  "userId": {
    "$oid": "64789e88a929c56fab48f296"
  }
},
{
  "_id": {
    "$oid": "64aa643396c84ecf94b147bc"
  },
  "recipe": {
    "$oid": "640cd5ac2d9fecf12e88980b"
  },
  "userId": {
    "$oid": "64aa60ef96c84ecf94b147a6"
  }
},
{
  "_id": {
    "$oid": "64ad4e07700193407d47dbeb"
  },
  "recipe": {
    "$oid": "640cd5ac2d9fecf12e889855"
  },
  "userId": {
    "$oid": "64ad4dc9700193407d47dbd6"
  }
},
{
  "_id": {
    "$oid": "64ad4e2b700193407d47dbff"
  },
  "recipe": {
    "$oid": "640cd5ac2d9fecf12e889808"
  },
  "userId": {
    "$oid": "64ad4dc9700193407d47dbd6"
  }
},
{
  "_id": {
    "$oid": "64ada1bc175f1bcf51d7ffa6"
  },
  "recipe": {
    "$oid": "640cd5ac2d9fecf12e889811"
  },
  "userId": {
    "$oid": "64ada192175f1bcf51d7ff8f"
  }
},
{
  "_id": {
    "$oid": "64aee97def41a3058fe13bfd"
  },
  "recipe": {
    "$oid": "640cd5ac2d9fecf12e889812"
  },
  "userId": {
    "$oid": "64aee655ef41a3058fe13b5c"
  }
},
{
  "_id": {
    "$oid": "64aee99eef41a3058fe13c0c"
  },
  "recipe": {
    "$oid": "640cd5ac2d9fecf12e889808"
  },
  "userId": {
    "$oid": "64aee655ef41a3058fe13b5c"
  }
},
{
  "_id": {
    "$oid": "64aee9a5ef41a3058fe13c1b"
  },
  "recipe": {
    "$oid": "640cd5ac2d9fecf12e88984e"
  },
  "userId": {
    "$oid": "64aee655ef41a3058fe13b5c"
  }
},
{
  "_id": {
    "$oid": "64aee9acef41a3058fe13c2a"
  },
  "recipe": {
    "$oid": "640cd5ac2d9fecf12e889826"
  },
  "userId": {
    "$oid": "64aee655ef41a3058fe13b5c"
  }
},
{
  "_id": {
    "$oid": "64aee9f3ef41a3058fe13c37"
  },
  "recipe": {
    "$oid": "640cd5ac2d9fecf12e889814"
  },
  "userId": {
    "$oid": "64aee655ef41a3058fe13b5c"
  }
},
{
  "_id": {
    "$oid": "64afc59dae19126ae7aef4c8"
  },
  "recipe": {
    "$oid": "640cd5ac2d9fecf12e889808"
  },
  "userId": {
    "$oid": "64afb86eaad8101d4dda100a"
  }
},
{
  "_id": {
    "$oid": "64b0f644ff33c145cc272e5a"
  },
  "recipe": {
    "$oid": "640cd5ac2d9fecf12e889864"
  },
  "userId": {
    "$oid": "64afb86eaad8101d4dda100a"
  }
},
{
  "_id": {
    "$oid": "64b63eebf66b4e4a1a205bcb"
  },
  "recipe": {
    "$oid": "640cd5ac2d9fecf12e889804"
  },
  "userId": {
    "$oid": "64b63cc4f66b4e4a1a205b9a"
  }
},
{
  "_id": {
    "$oid": "64b7a9aa1e7bfae64e5cc283"
  },
  "recipe": {
    "$oid": "640cd5ac2d9fecf12e8897f8"
  },
  "userId": {
    "$oid": "64ac3dbbf32ca7a275a1b367"
  }
},
{
  "_id": {
    "$oid": "64b7a9b51e7bfae64e5cc294"
  },
  "recipe": {
    "$oid": "640cd5ac2d9fecf12e889803"
  },
  "userId": {
    "$oid": "64ac3dbbf32ca7a275a1b367"
  }
},
{
  "_id": {
    "$oid": "64b7a9ba1e7bfae64e5cc2a2"
  },
  "recipe": {
    "$oid": "640cd5ac2d9fecf12e8897fd"
  },
  "userId": {
    "$oid": "64ac3dbbf32ca7a275a1b367"
  }
},
{
  "_id": {
    "$oid": "64b7a9c21e7bfae64e5cc2b0"
  },
  "recipe": {
    "$oid": "640cd5ac2d9fecf12e8897f4"
  },
  "userId": {
    "$oid": "64ac3dbbf32ca7a275a1b367"
  }
},
{
  "_id": {
    "$oid": "64b7a9c81e7bfae64e5cc2be"
  },
  "recipe": {
    "$oid": "640cd5ac2d9fecf12e889801"
  },
  "userId": {
    "$oid": "64ac3dbbf32ca7a275a1b367"
  }
},
{
  "_id": {
    "$oid": "64b7a9d21e7bfae64e5cc2d0"
  },
  "recipe": {
    "$oid": "640cd5ac2d9fecf12e8897f2"
  },
  "userId": {
    "$oid": "64ac3dbbf32ca7a275a1b367"
  }
},
{
  "_id": {
    "$oid": "64b7a9d71e7bfae64e5cc2de"
  },
  "recipe": {
    "$oid": "640cd5ac2d9fecf12e889806"
  },
  "userId": {
    "$oid": "64ac3dbbf32ca7a275a1b367"
  }
},
{
  "_id": {
    "$oid": "64b7a9db1e7bfae64e5cc2ed"
  },
  "recipe": {
    "$oid": "640cd5ac2d9fecf12e889856"
  },
  "userId": {
    "$oid": "64ac3dbbf32ca7a275a1b367"
  }
},
{
  "_id": {
    "$oid": "64b7a9e01e7bfae64e5cc2fc"
  },
  "recipe": {
    "$oid": "640cd5ac2d9fecf12e88985b"
  },
  "userId": {
    "$oid": "64ac3dbbf32ca7a275a1b367"
  }
},
{
  "_id": {
    "$oid": "64b7a9e71e7bfae64e5cc30b"
  },
  "recipe": {
    "$oid": "640cd5ac2d9fecf12e889818"
  },
  "userId": {
    "$oid": "64ac3dbbf32ca7a275a1b367"
  }
},
{
  "_id": {
    "$oid": "64bb070ddeaa6ae9731b07ee"
  },
  "recipe": {
    "$oid": "640cd5ac2d9fecf12e8897f8"
  },
  "userId": {
    "$oid": "6431d37d34a783fc11633793"
  }
},
{
  "_id": {
    "$oid": "64bbe7affe1d3c41b88dd787"
  },
  "recipe": {
    "$oid": "640cd5ac2d9fecf12e889855"
  },
  "userId": {
    "$oid": "6431d37d34a783fc11633793"
  }
},
{
  "_id": {
    "$oid": "64bd38e2c6c74dc55e376063"
  },
  "recipe": {
    "$oid": "640cd5ac2d9fecf12e8898b1"
  },
  "userId": {
    "$oid": "64addf4d78996aa84d343b32"
  }
},
{
  "_id": {
    "$oid": "64bd38f8c6c74dc55e37608d"
  },
  "recipe": {
    "$oid": "640cd5ac2d9fecf12e88982f"
  },
  "userId": {
    "$oid": "64addf4d78996aa84d343b32"
  }
},
{
  "_id": {
    "$oid": "64bd38ffc6c74dc55e3760a5"
  },
  "recipe": {
    "$oid": "640cd5ac2d9fecf12e889821"
  },
  "userId": {
    "$oid": "64addf4d78996aa84d343b32"
  }
},
{
  "_id": {
    "$oid": "64bd3a52c6c74dc55e3761cf"
  },
  "recipe": {
    "$oid": "640cd5ac2d9fecf12e88981a"
  },
  "userId": {
    "$oid": "64addf4d78996aa84d343b32"
  }
},
{
  "_id": {
    "$oid": "64bd59b2e2773465a1566232"
  },
  "recipe": {
    "$oid": "640cd5ac2d9fecf12e889811"
  },
  "userId": {
    "$oid": "6431d37d34a783fc11633793"
  }
},
{
  "_id": {
    "$oid": "64bd59b9e2773465a1566250"
  },
  "recipe": {
    "$oid": "640cd5ac2d9fecf12e889830"
  },
  "userId": {
    "$oid": "6431d37d34a783fc11633793"
  }
},
{
  "_id": {
    "$oid": "64bd59e4e2773465a15662a1"
  },
  "recipe": {
    "$oid": "640cd5ac2d9fecf12e88980d"
  },
  "userId": {
    "$oid": "6431d37d34a783fc11633793"
  }
},
{
  "_id": {
    "$oid": "64bd59e8e2773465a15662b9"
  },
  "recipe": {
    "$oid": "640cd5ac2d9fecf12e889851"
  },
  "userId": {
    "$oid": "6431d37d34a783fc11633793"
  }
},
{
  "_id": {
    "$oid": "65241918e64fb1e1bc61ddd4"
  },
  "recipe": {
    "$oid": "640cd5ac2d9fecf12e889855"
  },
  "userId": {
    "$oid": "652418d6e64fb1e1bc61dd9c"
  }
},
{
  "_id": {
    "$oid": "67941987379e00643dc53c12"
  },
  "recipe": "640cd5ac2d9fecf12e889831",
  "userId": "643050fde2d754d8e3549c33",
  "_class": "corp.soyummy.userfavorites.UserFavorite"
},
{
  "_id": {
    "$oid": "679443353c9b9f1b2c16ca31"
  },
  "recipe": "640cd5ac2d9fecf12e8897f6",
  "userId": "67911ba5171e5c4585004236",
  "_class": "corp.soyummy.userfavorites.UserFavorite"
}]